{"State.f2f0975b-3354-469f-91b2-795515bbd25b": {"id": "f2f0975b-3354-469f-91b2-795515bbd25b", "created_at": "2022-12-06T15:40:17.404788", "updated_at": "2022-12-06T15:40:17.404849", "name": "California", "__class__": "State"}, "State.8ada90e2-30a8-4356-951e-aa67ff74afb8": {"id": "8ada90e2-30a8-4356-951e-aa67ff74afb8", "created_at": "2022-12-06T15:40:17.405522", "updated_at": "2022-12-06T15:40:17.405566", "name": "Arizona", "__class__": "State"}, "Place.a3c2916a-aa4f-45d5-b0c3-174d84ddde80": {"id": "a3c2916a-aa4f-45d5-b0c3-174d84ddde80", "created_at": "2022-12-06T15:40:17.406322", "updated_at": "2022-12-06T15:40:17.413829", "city_id": "0001", "user_id": "0001", "name": "My little house", "number_rooms": 4, "number_bathrooms": 2, "max_guest": 10, "price_by_night": 300, "latitude": 37.773972, "longitude": -122.431297, "__class__": "Place"}, "State.5a818f3e-3472-4671-ad4d-78cedc9d98fc": {"id": "5a818f3e-3472-4671-ad4d-78cedc9d98fc", "created_at": "2022-12-06T15:45:44.886402", "updated_at": "2022-12-06T15:45:44.886502", "name": "California", "__class__": "State"}, "State.37aeafd3-c376-4cc8-aec1-df4276a6a24a": {"id": "37aeafd3-c376-4cc8-aec1-df4276a6a24a", "created_at": "2022-12-06T15:45:44.887242", "updated_at": "2022-12-06T15:45:44.887284", "name": "Arizona", "__class__": "State"}, "Place.6d93f9f3-b86d-4418-bdf3-68410cee099d": {"id": "6d93f9f3-b86d-4418-bdf3-68410cee099d", "created_at": "2022-12-06T15:45:44.887998", "updated_at": "2022-12-06T15:45:44.895041", "city_id": "0001", "user_id": "0001", "name": "My little house", "number_rooms": 4, "number_bathrooms": 2, "max_guest": 10, "price_by_night": 300, "latitude": 37.773972, "longitude": -122.431297, "__class__": "Place"}}